vam_buk_007/__init__.py
vam_buk_007/example.py
vam_buk_007-0.0.3.dist-info/LICENSE
vam_buk_007-0.0.3.dist-info/METADATA
vam_buk_007-0.0.3.dist-info/WHEEL
vam_buk_007-0.0.3.dist-info/top_level.txt
vam_buk_007-0.0.3.dist-info/RECORD
