Metadata-Version: 2.1
Name: vam_buk_007
Version: 0.0.3
Summary: Simple addtion program
Author-email: Vamshi Bukya <vamshivamshi148@gmail.com>
Project-URL: Homepage, https://github.com/vamshi007/learning_git
Project-URL: Issues, https://github.com/vamshi007/Supply_chain
Classifier: Programming Language :: Python :: 3
Classifier: License :: OSI Approved :: MIT License
Classifier: Operating System :: OS Independent
Requires-Python: >=3.6
License-File: LICENSE
